pessimist/__init__.py
pessimist/__main__.py
pessimist/cli.py
pessimist/manager.py
pessimist/util.py
pessimist-0.9.3.dist-info/LICENSE
pessimist-0.9.3.dist-info/METADATA
pessimist-0.9.3.dist-info/WHEEL
pessimist-0.9.3.dist-info/entry_points.txt
pessimist-0.9.3.dist-info/top_level.txt
pessimist-0.9.3.dist-info/RECORD
