Metadata-Version: 2.1
Name: pessimist
Version: 0.9.3
Summary: Ensures your dependencies work with minimum version
Home-page: https://github.com/python-packaging/pessimist/
Author: Tim Hatch
Author-email: tim@timhatch.com
License: MIT
Platform: UNKNOWN
Requires-Python: >=3.6
Requires-Dist: volatile (>=1.0)
Requires-Dist: toml (>=0.10.2)
Requires-Dist: pep517 (>=0.6.0)
Requires-Dist: honesty (==0.3.0a2)
Requires-Dist: highlighter (>=0.1.1)
Requires-Dist: setuptools (>=48.0.0)
Requires-Dist: click (>=7.1.2)
